<odoo>
    <p style="margin:0px 0 12px 0;box-sizing:border-box;">
        <p>
            <span style="text-decoration:none;box-sizing:border-box;background-color:transparent;">
                <strong t-out="object.genre" data-oe-t-inline="true" style="box-sizing:border-box;font-weight: bolder;" contenteditable="false">GENRE</strong>
            </span>
            <span style="text-decoration:none;box-sizing:border-box;background-color:transparent;">
                <strong t-out="object.name" data-oe-t-inline="true" style="box-sizing:border-box;font-weight: bolder;" contenteditable="false">NOM PRENOM</strong>
            </span>
            ,comme convenu, vous trouverez ci-dessous un résumé des points évoqués lors de notre échange téléphonique de ce jour.
        </p>
        <br><br>
        <p>Ela France est une société jeune et dynamique spécialisée dans le conseil en recrutement qui accompagne ses candidats dans le processus d’emploi.</p>
        <br><br>
        <p>Nous avons le plaisir de vous annoncer que nous avons sélectionné votre CV suite à votre candidature au poste 
            <span style="text-decoration:none;box-sizing:border-box;background-color:transparent;">
                <strong t-out="object.job_id.name" data-oe-t-inline="true" style="box-sizing:border-box;font-weight: bolder;" contenteditable="false">POSTE</strong>
            </span>.
        </p>        
        <br>
        <p>Afin d'optimiser votre recrutement et ainsi respecter le cahier des charges de nos partenaires nous souhaitons vous accompagner dans votre certification :
            <span style="text-decoration:none;box-sizing:border-box;background-color:transparent;">
                <strong t-out="object.certification.name" data-oe-t-inline="true" style="box-sizing:border-box;font-weight: bolder;" contenteditable="false">CERTIFICATION</strong>
            </span>
        </p>.
        <br><br>
    </p>
    <p style="margin:0px 0 12px 0;box-sizing:border-box;">
        <p>Pour ce faire :</p>
    </p>
    <br>
    <p style="margin:0px 0 12px 0;box-sizing:border-box;">
        <span style="color: #222222; font-size: small">• Vous disposez d'un moyen de connexion pour accéder à une formation uniquement en ligne</span>
        <br>
        <span style="color: #222222; font-size: small">• 
<span style="text-decoration:none;box-sizing:border-box;background-color:transparent;"><strong t-out="object.nombre_dheures" data-oe-t-inline="true" style="box-sizing:border-box;font-weight: bolder;" contenteditable="false">NOMBRE D'HEURES</strong></span>
 H de formation minimum</span><br><span style="color: #222222; font-size: small"><font class="text-o-color-5" style="box-sizing:border-box;color:#383e45;">• Premier appel de la conseillère pédagogique &nbsp;le </font><font style="box-sizing: border-box; color: #6ba54a;">09/06/22 à 12H00 (HORAIRE ET DATE "1er Rdv Pédagogique")</font></span></p><p style="margin:0px 0 12px 0;box-sizing:border-box;"><b style="box-sizing:border-box;font-weight:500;"><span style="color: #222222; font-size: small"><font class="text-o-color-5" style="box-sizing:border-box;color:#383e45;font-weight: normal;">•&nbsp;</font></span><font class="text-o-color-5" style="box-sizing:border-box;color:#383e45;font-weight: 400;">RDV avec la responsable ressources humaines le </font><font style="box-sizing: border-box; color: #6ba54a; font-weight: 400;">09/05/22 à 11h30 <span style="color: #6ba54a; font-size: small">(HORAIRE ET DATE "RDV RH1")</span></font>
            </b>
            <br><br>
            Comment ELA France vous accompagne :<br>• Accompagnement des démarches d'inscription<br>• Conseil et encadrement tout le long du cycle de recrutement<br>• Engagement de points hebdomadaire avec un directeur pédagogique<br>• Vous proposer des postes répondant à votre profil et à vos attentes&nbsp;dans nos sociétés partenaires<br><br>Nous nous tenons à votre entière disposition pour toutes demandes complémentaires.</p><p style="margin:0px 0 12px 0;box-sizing:border-box;"><br>Bien cordialement,</p><p style="margin:0px 0 12px 0;box-sizing:border-box;"><br></p>
        <p style="margin:0px 0 12px 0;box-sizing:border-box;">
        <!-- FOOTER -->
        <t t-if="user.signature" data-oe-t-group-active="true" data-oe-t-group="0" data-oe-t-inline="true">
            <t t-out="user.signature" data-oe-t-inline="true" contenteditable="false">Signature</t>
        </t>
    </p>
</odoo>